slippi/__init__.py
slippi/custom_logging.py
slippi/main.py
slippi/slippi_api.py
slippi/slippi_characters.py
slippi/slippi_ranks.py
slippi/slippi_user.py
slippi/tests/__init__.py
slippi/tests/test_slippi_api.py
slippi/tests/test_slippi_characters.py
slippi/tests/test_slippi_ranks.py
slippi/tests/test_slippi_user.py
slippy_api-1.9.dist-info/licenses/LICENSE
slippy_api-1.9.dist-info/METADATA
slippy_api-1.9.dist-info/WHEEL
slippy_api-1.9.dist-info/top_level.txt
slippy_api-1.9.dist-info/RECORD
