Metadata-Version: 2.4
Name: slippy_api
Version: 1.9
Summary: API wrapper for slippi.gg
Home-page: https://github.com/ConstObject/slippy-api
Author: Sophia
Author-email: sophimander@gmail.com
Classifier: Programming Language :: Python :: 3
Classifier: License :: OSI Approved :: MIT License
Classifier: Operating System :: OS Independent
Requires-Python: >=3.6
License-File: LICENSE
Requires-Dist: requests~=2.29.0
Requires-Dist: ratelimiter~=1.2.0.post0
Requires-Dist: pytest~=7.3.1
Dynamic: author
Dynamic: author-email
Dynamic: classifier
Dynamic: description
Dynamic: description-content-type
Dynamic: home-page
Dynamic: license-file
Dynamic: requires-dist
Dynamic: requires-python
Dynamic: summary
